dgpytest/__init__.py
dgpytest/__main__.py
dgpytest/_meta.py
dgpytest/hooks.py
dgpytest/plugin.py
dgpytest/py.typed
dgpytest-0.0.2.dist-info/entry_points.txt
dgpytest-0.0.2.dist-info/LICENSE
dgpytest-0.0.2.dist-info/METADATA
dgpytest-0.0.2.dist-info/WHEEL
dgpytest-0.0.2.dist-info/RECORD
